<NomaiObject xmlns:xsi="http://www.w3.org/2001/XMLSchema-instance" xsi:noNamespaceSchemaLocation="https://raw.githubusercontent.com/Outer-Wilds-New-Horizons/new-horizons/main/NewHorizons/Schemas/text_schema.xsd">
	<TextBlock>
		<ID>1</ID>
		<LocationA />
		<Text>Luma: According to all known laws of aviation, there is no way a bee should be able to fly.</Text>
	</TextBlock>
	<TextBlock>
		<ID>2</ID>
		<ParentID>1</ParentID>
		<LocationB />
		<Text>Luma: Its wings are too small to get its fat little body off the ground.</Text>
	</TextBlock>
	<TextBlock>
		<ID>3</ID>
		<ParentID>2</ParentID>
		<LocationA />
		<Text>Luma: The bee, of course, flies anyway because bees don't care what humans think is impossible.</Text>
	</TextBlock>
	<TextBlock>
		<ID>4</ID>
		<ParentID>3</ParentID>
		<LocationA />
		<Text>Barry: Yellow, black.</Text>
	</TextBlock>
	<TextBlock>
		<ID>5</ID>
		<ParentID>4</ParentID>
		<LocationA />
		<Text>Barry: Yellow, black.</Text>
	</TextBlock>
	<TextBlock>
		<ID>6</ID>
		<ParentID>5</ParentID>
		<LocationA />
		<Text>Barry: Yellow, black.</Text>
	</TextBlock>
	<TextBlock>
		<ID>7</ID>
		<ParentID>6</ParentID>
		<LocationA />
		<Text>Barry: Yellow, black.</Text>
	</TextBlock>
	<TextBlock>
		<ID>8</ID>
		<ParentID>7</ParentID>
		<LocationA />
		<Text>Barry: Ooh, black and yellow!</Text>
	</TextBlock>
	<TextBlock>
		<ID>9</ID>
		<ParentID>3</ParentID>
		<LocationA />
		<Text>Janet: Barry! Breakfast is ready!</Text>
	</TextBlock>
	<TextBlock>
		<ID>10</ID>
		<ParentID>9</ParentID>
		<LocationA />
		<Text>Barry: Coming!</Text>
	</TextBlock>
</NomaiObject>